README.md
setup.py
portable_es/__init__.py
portable_es/compat.py
portable_es/hybrid.py
portable_es/optimizers.py
portable_es/portable_es.py
portable_es/sac.py
portable_es/scheduler.py
portable_es/timing.py
portable_es/utils.py
portable_es.egg-info/PKG-INFO
portable_es.egg-info/SOURCES.txt
portable_es.egg-info/dependency_links.txt
portable_es.egg-info/requires.txt
portable_es.egg-info/top_level.txt