Metadata-Version: 2.1
Name: portable-es
Version: 1.4.1
Summary: Portable ES is a distributed gradient-less optimization framework built on PyTorch & Numpy.
Home-page: https://github.com/ob-trading/portable-es
Author: Casper
Author-email: casper@devdroplets.com
License: MPL2
Platform: UNKNOWN
Classifier: Development Status :: 4 - Beta
Classifier: Intended Audience :: Developers
Classifier: Intended Audience :: Science/Research
Classifier: License :: OSI Approved :: Mozilla Public License 2.0 (MPL 2.0)
Classifier: Programming Language :: Python :: 3
Classifier: Programming Language :: Python :: 3.5
Classifier: Programming Language :: Python :: 3.6
Classifier: Programming Language :: Python :: 3.7
Classifier: Programming Language :: Python :: 3.8
